cursofiap/__init__.py
cursofiap/core.py
cursofiap_machinelearning_package-1.0.0.dist-info/METADATA
cursofiap_machinelearning_package-1.0.0.dist-info/WHEEL
cursofiap_machinelearning_package-1.0.0.dist-info/top_level.txt
cursofiap_machinelearning_package-1.0.0.dist-info/RECORD
