Metadata-Version: 2.1
Name: cursofiap-machinelearning-package
Version: 1.0.0
Summary: Descricao da sua lib cursofiap
Home-page: https://github.com/tadrianonet/cursofiap
Author: Gabriel Hirai
Author-email: gabrielt.hirai@gmail.com
License: MIT
